mim/__init__.py
mim/__main__.py
mim/cli.py
mim/version.py
mim/click/__init__.py
mim/click/autocompletion.py
mim/click/compat.py
mim/click/customcommand.py
mim/click/option.py
mim/click/utils.py
mim/commands/__init__.py
mim/commands/download.py
mim/commands/gridsearch.py
mim/commands/install.py
mim/commands/list.py
mim/commands/run.py
mim/commands/search.py
mim/commands/test.py
mim/commands/train.py
mim/commands/uninstall.py
mim/utils/__init__.py
mim/utils/default.py
mim/utils/progress_bars.py
mim/utils/utils.py
openmim-0.3.9.dist-info/LICENSE
openmim-0.3.9.dist-info/METADATA
openmim-0.3.9.dist-info/WHEEL
openmim-0.3.9.dist-info/entry_points.txt
openmim-0.3.9.dist-info/top_level.txt
openmim-0.3.9.dist-info/RECORD
