Metadata-Version: 2.1
Name: openmim
Version: 0.3.9
Summary: MIM Installs OpenMMLab packages
Home-page: https://github.com/open-mmlab/mim
Author: MIM Authors
Author-email: openmmlab@gmail.com
Requires-Python: >=3.6
Provides-Extra: all
Provides-Extra: tests
License-File: LICENSE
